pyrq/__init__.py
pyrq/helpers.py
pyrq/pools.py
pyrq/queues.py
pyrq/unique_queues.py
py_rq-5.0.0.dist-info/LICENSE
py_rq-5.0.0.dist-info/METADATA
py_rq-5.0.0.dist-info/WHEEL
py_rq-5.0.0.dist-info/top_level.txt
py_rq-5.0.0.dist-info/RECORD
