Metadata-Version: 2.1
Name: py-rq
Version: 5.0.0
Summary: Redis queue for Python
Home-page: https://github.com/heureka/py-rq
Author: Heureka.cz
Author-email: podpora@heureka.cz
License: MIT
Platform: UNKNOWN
Requires-Dist: redis (<4,>=3.0.0)
